{
    "label": "RK SSP (5,3)",
    "A": [
        [
            "0",
            "0",
            "0",
            "0",
            "0"
        ],
        [
            "0.37726891511710",
            "0",
            "0",
            "0",
            "0"
        ],
        [
            "0.37726891511710",
            "0.37726891511710",
            "0",
            "0",
            "0"
        ],
        [
            "0.16352294089771",
            "0.16352294089771",
            "0.16352294089771",
            "0",
            "0"
        ],
        [
            "0.14904059394856",
            "0.14831273384724",
            "0.14831273384724",
            "0.34217696850008",
            "0"
        ]
    ],
    "b": [
        "0.19707596384481",
        "0.11780316509765",
        "0.11709725193772",
        "0.27015874934251",
        "0.29786487010104"
    ],
    "c": [
        "0",
        "0.37726891511710",
        "0.75453783023419",
        "0.49056882269314",
        "0.78784303014311"
    ],
    "doi": "10.1137/S0036142901389025"
}
